[{"id": 323, "name": "\u0e1b\u0e25\u0e32\u0e15\u0e30\u0e40\u0e1e\u0e35\u0e22\u0e19", "number": [47, 48, 748, 708, 418]}, {"id": 484, "name": "\u0e1b\u0e0f\u0e34\u0e01\u0e39\u0e25", "number": []}, {"id": 485, "name": "\u0e1b\u0e0f\u0e34\u0e17\u0e34\u0e19", "number": []}, {"id": 486, "name": "\u0e1b\u0e0f\u0e34\u0e21\u0e32", "number": [91, 92, 198, 199, 299]}, {"id": 487, "name": "\u0e1b\u0e23\u0e30\u0e01\u0e32\u0e28\u0e19\u0e35\u0e22\u0e1a\u0e31\u0e15\u0e23", "number": []}, {"id": 488, "name": "\u0e1b\u0e23\u0e30\u0e04\u0e33", "number": []}, {"id": 489, "name": "\u0e1b\u0e23\u0e30\u0e40\u0e04\u0e19", "number": []}, {"id": 490, "name": "\u0e1b\u0e23\u0e30\u0e42\u0e04\u0e21", "number": []}, {"id": 491, "name": "\u0e1b\u0e23\u0e30\u0e40\u0e08\u0e35\u0e22\u0e14", "number": [48, 49, 148, 149, 489]}, {"id": 492, "name": "\u0e1b\u0e23\u0e30\u0e41\u0e08", "number": []}, {"id": 493, "name": "\u0e1b\u0e23\u0e30\u0e14\u0e32\u0e19\u0e49\u0e33", "number": [47, 67, 247, 267, 276]}, {"id": 494, "name": "\u0e1b\u0e23\u0e30\u0e15\u0e39", "number": [24, 28, 124, 128, 248]}, {"id": 495, "name": "\u0e1b\u0e23\u0e30\u0e15\u0e39\u0e42\u0e1a\u0e2a\u0e16\u0e4c", "number": []}, {"id": 496, "name": "\u0e1b\u0e23\u0e30\u0e17\u0e31\u0e14", "number": []}, {"id": 497, "name": "\u0e1b\u0e23\u0e30\u0e40\u0e17\u0e35\u0e22\u0e1a", "number": [56, 57, 256, 367, 564]}, {"id": 498, "name": "\u0e1b\u0e23\u0e32\u0e07\u0e04\u0e4c", "number": []}, {"id": 499, "name": "\u0e1b\u0e23\u0e32\u0e2a\u0e32\u0e17", "number": [91, 97, 697, 191, 297]}, {"id": 500, "name": "\u0e1b\u0e25\u0e49\u0e19\u0e2a\u0e30\u0e14\u0e21", "number": [82, 86, 87, 286, 287, 872]}, {"id": 501, "name": "\u0e1b\u0e25\u0e27\u0e01", "number": [89, 86, 789, 889, 887]}, {"id": 502, "name": "\u0e1b\u0e25\u0e2d\u0e01", "number": [8, 9, 801, 901, 809]}, {"id": 503, "name": "\u0e1b\u0e25\u0e48\u0e2d\u0e07\u0e44\u0e1f", "number": [10, 18, 8, 180, 818, 89]}, {"id": 504, "name": "\u0e1b\u0e25\u0e2d\u0e1a\u0e42\u0e22\u0e19", "number": [6, 7, 8, 106, 207, 308]}, {"id": 505, "name": "\u0e1b\u0e25\u0e48\u0e2d\u0e22\u0e19\u0e01", "number": [86, 88, 868, 881, 882]}, {"id": 506, "name": "\u0e1b\u0e25\u0e32", "number": [88, 78, 287, 878, 808]}, {"id": 507, "name": "\u0e1b\u0e25\u0e32\u0e44\u0e2b\u0e25", "number": []}, {"id": 508, "name": "\u0e1b\u0e25\u0e32\u0e44\u0e2b\u0e25", "number": []}, {"id": 509, "name": "\u0e1b\u0e25\u0e34\u0e07", "number": [55, 28, 58, 585, 857, 568]}, {"id": 510, "name": "\u0e1b\u0e25\u0e39\u0e01", "number": [79, 91, 179, 918, 967]}, {"id": 511, "name": "\u0e1b\u0e49\u0e2d\u0e21", "number": []}, {"id": 512, "name": "\u0e1b\u0e31\u0e2a\u0e2a\u0e32\u0e27\u0e30", "number": [22, 27, 36, 227, 336]}, {"id": 513, "name": "\u0e1b\u0e32\u0e01", "number": []}, {"id": 514, "name": "\u0e1b\u0e32\u0e01\u0e01\u0e32", "number": []}, {"id": 515, "name": "\u0e1b\u0e48\u0e32\u0e40\u0e02\u0e32", "number": [43, 46, 53, 434, 465, 537]}, {"id": 516, "name": "\u0e1b\u0e48\u0e32\u0e0a\u0e49\u0e32", "number": []}, {"id": 517, "name": "\u0e1b\u0e35\u0e01", "number": []}, {"id": 518, "name": "\u0e1b\u0e35\u0e19\u0e40\u0e02\u0e32", "number": [97, 96, 297, 196, 996]}, {"id": 519, "name": "\u0e1b\u0e35\u0e28\u0e32\u0e08", "number": []}, {"id": 520, "name": "\u0e1b\u0e37\u0e19", "number": [18, 8, 188, 108, 883]}, {"id": 521, "name": "\u0e40\u0e1b\u0e47\u0e14\u0e44\u0e01\u0e48", "number": [89, 8, 788, 809, 789]}, {"id": 522, "name": "\u0e40\u0e1b\u0e47\u0e14\u0e44\u0e01\u0e48", "number": []}, {"id": 523, "name": "\u0e40\u0e1b\u0e48\u0e32", "number": []}, {"id": 524, "name": "\u0e40\u0e1b\u0e37\u0e49\u0e2d\u0e19", "number": []}, {"id": 525, "name": "\u0e41\u0e1b\u0e49\u0e07\u0e1c\u0e31\u0e14\u0e2b\u0e19\u0e49\u0e32", "number": []}, {"id": 526, "name": "\u0e41\u0e1b\u0e23\u0e07\u0e1c\u0e21", "number": []}, {"id": 527, "name": "\u0e41\u0e1b\u0e23\u0e07\u0e2a\u0e35\u0e1f\u0e31\u0e19", "number": []}, {"id": 528, "name": "\u0e44\u0e1b\u0e23\u0e29\u0e13\u0e35\u0e22\u0e4c", "number": []}, {"id": 606, "name": "\u0e1b\u0e25\u0e32", "number": []}]